click_creds/__init__.py
click_creds/classes.py
click_creds/decorators.py
click_creds/defaults.py
click_creds/groups.py
click_creds/utils.py
intelowl_click_creds-0.0.1.dist-info/LICENSE
intelowl_click_creds-0.0.1.dist-info/METADATA
intelowl_click_creds-0.0.1.dist-info/WHEEL
intelowl_click_creds-0.0.1.dist-info/top_level.txt
intelowl_click_creds-0.0.1.dist-info/RECORD
