Metadata-Version: 2.1
Name: intelowl-click-creds
Version: 0.0.1
Summary: Pluggable credentials storage and management for click CLI apps.
Home-page: https://github.com/intelowlproject/click-creds
Author: Eshaan Bansal
Author-email: eshaan7bansal@gmail.com
License: BSD
Project-URL: Documentation, https://github.com/intelowlproject/click-creds
Project-URL: Funding, https://www.paypal.me/eshaanbansal
Project-URL: Source, https://github.com/intelowlproject/click-creds
Project-URL: Tracker, https://github.com/intelowlproject/click-creds/issues
Keywords: click credentials creds netrc auth cli python store
Classifier: Development Status :: 5 - Production/Stable
Classifier: Intended Audience :: Developers
Classifier: Environment :: Web Environment
Classifier: License :: OSI Approved :: BSD License
Classifier: Programming Language :: Python :: 3
Classifier: Programming Language :: Python :: 3.6
Classifier: Programming Language :: Python :: 3.7
Classifier: Programming Language :: Python :: 3.8
Classifier: Programming Language :: Python :: 3.9
Classifier: Programming Language :: Python :: 3.10
Classifier: Topic :: Software Development :: Libraries :: Python Modules
Requires-Python: >=3.6
License-File: LICENSE
Requires-Dist: click (>=7.0)
Requires-Dist: tinynetrc (==1.3.1)
Provides-Extra: dev
Requires-Dist: black (==20.8b1) ; extra == 'dev'
Requires-Dist: flake8 (==3.8.4) ; extra == 'dev'
Requires-Dist: pre-commit (==2.9.2) ; extra == 'dev'
Requires-Dist: codecov ; extra == 'dev'
Requires-Dist: tox ; extra == 'dev'
Requires-Dist: tox-gh-actions ; extra == 'dev'
Requires-Dist: click (>=7.0) ; extra == 'dev'
Requires-Dist: tinynetrc (==1.3.1) ; extra == 'dev'
Provides-Extra: test
Requires-Dist: black (==20.8b1) ; extra == 'test'
Requires-Dist: flake8 (==3.8.4) ; extra == 'test'
Requires-Dist: pre-commit (==2.9.2) ; extra == 'test'
Requires-Dist: codecov ; extra == 'test'
Requires-Dist: tox ; extra == 'test'
Requires-Dist: tox-gh-actions ; extra == 'test'
Requires-Dist: click (>=7.0) ; extra == 'test'
Requires-Dist: tinynetrc (==1.3.1) ; extra == 'test'
